[
    {
        "content": "Get your housing in place so you can register your mail adress which is crucial in Sweden"
    },
    {
        "content": "Register your self at Tax authority(Skatteverket)"
    },
    {
        "content": "Apply for your personal ID card(ID kort) at Skatteverket also. "
    },
    {
        "content": "Register a bank account(SEB, SWED, NORDEA..)"
    },
    {
        "content": "Activate your mobile bank id. You can ask your bank to help to activate mobile bank id"
    }
]